{"cameraMode":{"drawMode":3,"name":"Shadow Cascades","section":"Miscellaneous"},"sceneLighting":false,"audioPlay":false,"sceneViewState":{"m_AlwaysRefresh":false,"showFog":true,"showSkybox":false,"showFlares":true,"showImageEffects":true,"showParticleSystems":true,"showVisualEffectGraphs":true,"m_FxEnabled":true},"in2DMode":false,"pivot":{"x":3.931816816329956,"y":2.3338820934295656,"z":-1.4979894161224366},"rotation":{"x":-0.16642872989177705,"y":0.56793212890625,"z":-0.11822909861803055,"w":-0.7979702353477478},"size":0.411825567483902,"orthographic":false}